pytwitcasting/__init__.py
pytwitcasting/__version__.py
pytwitcasting/api.py
pytwitcasting/auth.py
pytwitcasting/error.py
pytwitcasting/models.py
pytwitcasting/parsers.py
pytwitcasting/utils.py
pytwitcasting-1.0.0.dist-info/METADATA
pytwitcasting-1.0.0.dist-info/RECORD
pytwitcasting-1.0.0.dist-info/WHEEL
pytwitcasting-1.0.0.dist-info/top_level.txt
