Metadata-Version: 2.1
Name: pytwitcasting
Version: 1.0.0
Summary: TwitcastingのAPI2(β)のライブラリ
Home-page: https://github.com/tamago324/PyTwitcasting
Author: tamago324
Author-email: tamago324.tky@gmail.com
License: UNKNOWN
Platform: UNKNOWN
Requires-Python: !=3.0.*,!=3.1.*,!=3.2.*,!=3.3.*
Requires-Dist: requests (<3.0.0,>=2.0.1)
